fastapi_crud_admin/__init__.py
fastapi_crud_admin/admin.py
fastapi_crud_admin/enum.py
fastapi_crud_admin/meta.py
fastapi_crud_admin/router/__init__.py
fastapi_crud_admin/router/auth.py
fastapi_crud_admin/router/meta.py
fastapi_crud_admin/router/schema.py
fastapi_crud_admin/utils/__init__.py
fastapi_crud_admin/utils/auth.py
fastapi_crud_admin/utils/database.py
fastapi_crud_admin/utils/interceptor.py
fastapi_crud_admin/utils/pagination.py
fastapi_crud_admin/utils/repository.py
fastapi_crud_admin/utils/router.py
fastapi_crud_admin-0.0.5.dist-info/METADATA
fastapi_crud_admin-0.0.5.dist-info/WHEEL
fastapi_crud_admin-0.0.5.dist-info/RECORD
