Metadata-Version: 2.1
Name: fastapi-crud-admin
Version: 0.0.5
Summary: 
Author: pingusoo
Author-email: als95.dev@gmail.com
Requires-Python: >=3.8,<4.0
Classifier: Programming Language :: Python :: 3
Classifier: Programming Language :: Python :: 3.8
Classifier: Programming Language :: Python :: 3.9
Classifier: Programming Language :: Python :: 3.10
Classifier: Programming Language :: Python :: 3.11
Requires-Dist: aiosqlite (>=0.19.0,<0.20.0)
Requires-Dist: fastapi (>=0.95.1,<0.96.0)
Requires-Dist: fastapi-pagination (>=0.12.15,<0.13.0)
Requires-Dist: sqlalchemy (>=1.4.46,<2.0.0)
